quizy/__init__.py
quizy/ai_generator.py
quizy/cli.py
quizy/core.py
quizy/mcp_server.py
quizy-0.4.8.dist-info/METADATA
quizy-0.4.8.dist-info/WHEEL
quizy-0.4.8.dist-info/entry_points.txt
quizy-0.4.8.dist-info/top_level.txt
quizy-0.4.8.dist-info/RECORD
