Metadata-Version: 2.4
Name: quizy
Version: 0.4.8
Summary: A simple, elegant Python framework for creating and running interactive quizzes
Author-email: Rustam Karimov <karimov.rustam.live@gmail.com>
License: MIT
Project-URL: Homepage, https://github.com/rustampy/quizy
Project-URL: Repository, https://github.com/rustampy/quizy
Project-URL: Documentation, https://github.com/rustampy/quizy#readme
Project-URL: Bug Tracker, https://github.com/rustampy/quizy/issues
Keywords: quiz,education,learning,interactive,assessment,testing
Classifier: Development Status :: 4 - Beta
Classifier: Intended Audience :: Education
Classifier: Intended Audience :: Developers
Classifier: Topic :: Education :: Testing
Classifier: Topic :: Software Development :: Libraries :: Python Modules
Classifier: Programming Language :: Python :: 3.10
Classifier: Programming Language :: Python :: 3.11
Classifier: Programming Language :: Python :: 3.12
Classifier: Programming Language :: Python :: 3.13
Classifier: License :: OSI Approved :: MIT License
Classifier: Operating System :: OS Independent
Requires-Python: >=3.8
Requires-Dist: openai>=2.0.0
Provides-Extra: openai
Provides-Extra: mcp
Requires-Dist: mcp>=1.24.0; extra == "mcp"
Provides-Extra: dev
Requires-Dist: pytest>=9.0.0; extra == "dev"
Requires-Dist: pytest-asyncio>=1.3.0; extra == "dev"
Requires-Dist: pytest-cov>=7.0.0; extra == "dev"
